sppm/__init__.py
shakshippm_31-0.1.2.dist-info/LICENSE
shakshippm_31-0.1.2.dist-info/METADATA
shakshippm_31-0.1.2.dist-info/WHEEL
shakshippm_31-0.1.2.dist-info/top_level.txt
shakshippm_31-0.1.2.dist-info/RECORD
